LICENSE
MANIFEST.in
README.md
pyproject.toml
setup.cfg
setup.py
tests/__init__.py
tests/testapp/__init__.py
tests/testapp/manage.py
tests/testapp/core/__init__.py
tests/testapp/core/tests.py
tests/testapp/core/migrations/__init__.py
tests/testapp/testapp/__init__.py
tests/testapp/testapp/asgi.py
tests/testapp/testapp/settings.py
tests/testapp/testapp/urls.py
tests/testapp/testapp/wsgi.py
wagtail_alerts/__init__.py
wagtail_alerts/alert.py
wagtail_alerts/alert_types.py
wagtail_alerts/apps.py
wagtail_alerts/bases.py
wagtail_alerts/blocks.py
wagtail_alerts/models.py
wagtail_alerts/settings.py
wagtail_alerts/tests.py
wagtail_alerts/urls.py
wagtail_alerts/views.py
wagtail_alerts/wagtail_hooks.py
wagtail_alerts.egg-info/PKG-INFO
wagtail_alerts.egg-info/SOURCES.txt
wagtail_alerts.egg-info/dependency_links.txt
wagtail_alerts.egg-info/requires.txt
wagtail_alerts.egg-info/top_level.txt
wagtail_alerts/migrations/0001_initial.py
wagtail_alerts/migrations/__init__.py
wagtail_alerts/migrations/__pycache__/0001_initial.cpython-311.pyc
wagtail_alerts/migrations/__pycache__/0002_alter_alertsettings_alerts.cpython-311.pyc
wagtail_alerts/migrations/__pycache__/0003_alter_alertsettings_alerts.cpython-311.pyc
wagtail_alerts/migrations/__pycache__/0004_alter_alertsettings_alerts.cpython-311.pyc
wagtail_alerts/migrations/__pycache__/0005_alter_alertsettings_alerts.cpython-311.pyc
wagtail_alerts/migrations/__pycache__/0006_alter_alertsettings_alerts.cpython-311.pyc
wagtail_alerts/migrations/__pycache__/0007_alter_alertsettings_alerts.cpython-311.pyc
wagtail_alerts/migrations/__pycache__/0008_alter_alertsettings_alerts.cpython-311.pyc
wagtail_alerts/migrations/__pycache__/0009_alter_alertsettings_alerts.cpython-311.pyc
wagtail_alerts/migrations/__pycache__/__init__.cpython-311.pyc
wagtail_alerts/static/wagtail_alerts/js/wagtail_alerts.js
wagtail_alerts/templates/wagtail_alerts/blocks/alert.html
wagtail_alerts/templates/wagtail_alerts/blocks/toast.html
wagtail_alerts/templates/wagtail_alerts/blocks/forms/alert_dates_settings.html
wagtail_alerts/templates/wagtail_alerts/blocks/forms/alert_settings.html
wagtail_alerts/templates/wagtail_alerts/tags/alerts.html
